{"name": "Hey Ram", "director": ["Kamal Haasan"], "country": "India", "language": ["Tamil", "Hindi"], "poster": "https://m.media-amazon.com/images/M/MV5BNGU4YWE1OWMtNDAyYS00MjVjLWI0MTItNzJkZTE0NzkzZDY4XkEyXkFqcGdeQXVyODEzOTQwNTY@._V1_QL75_UY281_CR8,0,190,281_.jpg", "bio": "Saketh Ram's wife is raped and killed during direct action day riots in Calcutta. He is convinced that Mahatma Gandhi is responsible for all the problems happening in the country and sets ou... Read all", "genre": ["Crime", "Drama", "History"], "runtime": 186}