{"name": "Pranchiyettan and the Saint", "director": ["Ranjith"], "country": "India", "language": ["Malayalam"], "poster": "https://m.media-amazon.com/images/M/MV5BMDg3ZjUxMDMtNmM2OC00MzNlLWEyMTgtMTI1Njk0OTdkMjZkXkEyXkFqcGdeQXVyNTI0NzYwMzE@._V1_QL75_UX190_CR0,30,190,281_.jpg", "bio": "Pranchiyettan is a successful businessman who often has talks with an imaginary St. Francis of Assisi. The story deals with how he goes about changing his embarrassing image to making a name... Read all", "genre": ["Comedy", "Drama"], "runtime": 140}